cloud_db_connector/__init__.py
cloud_db_connector/database_manager.py
cloud_db_connector/db_connection.py
cloud_db_connector/rds_execute.py
cloud_db_connector-0.2.4.dist-info/LICENSE
cloud_db_connector-0.2.4.dist-info/METADATA
cloud_db_connector-0.2.4.dist-info/WHEEL
cloud_db_connector-0.2.4.dist-info/top_level.txt
cloud_db_connector-0.2.4.dist-info/RECORD
