Metadata-Version: 2.2
Name: cloud_db_connector
Version: 0.2.4
Summary: A unified cloud db package for AWS, Azure, and GCP
Author: Aaditya Muleva
Author-email: aaditya.muleva@trovehealth.io
License: MIT
Classifier: Programming Language :: Python :: 3
Classifier: License :: OSI Approved :: MIT License
Classifier: Operating System :: OS Independent
Classifier: Development Status :: 5 - Production/Stable
Classifier: Intended Audience :: Developers
Classifier: Topic :: Software Development :: Libraries :: Python Modules
Requires-Python: >=3.6
License-File: LICENSE
Requires-Dist: boto3
Requires-Dist: pymysql>=1.0.2
Requires-Dist: pyodbc>=4.0.32
Requires-Dist: google-auth>=2.0.0
Requires-Dist: google-auth-oauthlib>=0.4.0
Requires-Dist: cryptography>=3.3.2
Requires-Dist: pyopenssl>=20.0.1
Dynamic: author
Dynamic: author-email
Dynamic: classifier
Dynamic: description
Dynamic: description-content-type
Dynamic: license
Dynamic: requires-dist
Dynamic: requires-python
Dynamic: summary
